lpdensity/__init__.py
lpdensity/lpbwdensity.py
lpdensity/lpbwdensity_fn.py
lpdensity/lpdensity.py
lpdensity/lpdensity_fn.py
lpdensity-2.4.1.dist-info/METADATA
lpdensity-2.4.1.dist-info/WHEEL
lpdensity-2.4.1.dist-info/top_level.txt
lpdensity-2.4.1.dist-info/RECORD
