Metadata-Version: 2.1
Name: lpdensity
Version: 2.4.1
Summary: Implements local polynomial point estimation with robust bias-corrected uniform confidence intervals.
Home-page: https://github.com/nppackages/lpdensity
Author: Rajita Chandak
Author-email: rchandak@princeton.edu
Project-URL: Bug Tracker, https://github.com/nppackages/lpdensity/issues
Classifier: Programming Language :: Python :: 3
Classifier: License :: OSI Approved :: MIT License
Classifier: Operating System :: OS Independent
Requires-Python: >=3.7
Requires-Dist: numpy
Requires-Dist: pandas
Requires-Dist: scipy
Requires-Dist: sympy
Requires-Dist: plotnine
